bloxapi/__init__.py
bloxapi/client.py
bloxapi/utils.py
bloxypy-0.1.9.dist-info/licenses/LICENSE
bloxypy-0.1.9.dist-info/METADATA
bloxypy-0.1.9.dist-info/WHEEL
bloxypy-0.1.9.dist-info/top_level.txt
bloxypy-0.1.9.dist-info/RECORD
