Metadata-Version: 2.4
Name: bloxypy
Version: 0.1.9
Summary: Advanced roblox wrapper for the Roblox API.
Home-page: https://github.com/jamiezon/ropython
Author: jamiezon
Author-email: jamiezon <jamiezon39@gmail.com>
Project-URL: Homepage, https://github.com/jamiezon/ropython
Project-URL: Bug Tracker, https://github.com/jamiezon/ropython/issues
Classifier: Development Status :: 3 - Alpha
Classifier: Intended Audience :: Developers
Classifier: License :: OSI Approved :: MIT License
Classifier: Operating System :: OS Independent
Classifier: Programming Language :: Python :: 3
Classifier: Programming Language :: Python :: 3.7
Classifier: Programming Language :: Python :: 3.8
Classifier: Programming Language :: Python :: 3.9
Classifier: Programming Language :: Python :: 3.10
Classifier: Programming Language :: Python :: 3.11
Requires-Python: >=3.7
License-File: LICENSE
Requires-Dist: pycryptodome
Requires-Dist: requests>=2.25.0
Dynamic: author
Dynamic: home-page
Dynamic: license-file
Dynamic: requires-python
